{
  "Monday": {
    "06:00 AM": "wake up & walk",
    "07:00 AM": "study gk",
    "08:00 AM": "",
    "09:00 AM": "",
    "10:00 AM": "",
    "11:00 AM": "",
    "12:00 PM": "",
    "01:00 PM": "",
    "02:00 PM": "break",
    "03:00 PM": "",
    "04:00 PM": "",
    "05:00 PM": "All daily quizz",
    "06:00 PM": "",
    "07:00 PM": "",
    "08:00 PM": "",
    "09:00 PM": "Mock tests"
  },
  "Tuesday": {
    "06:00 AM": "wake up & walk",
    "07:00 AM": "study gk",
    "08:00 AM": "",
    "09:00 AM": "",
    "10:00 AM": "break",
    "11:00 AM": "",
    "12:00 PM": "",
    "01:00 PM": "",
    "02:00 PM": "break",
    "03:00 PM": "",
    "04:00 PM": "",
    "05:00 PM": "All daily quizz",
    "06:00 PM": "",
    "07:00 PM": "",
    "08:00 PM": "",
    "09:00 PM": ""
  },
  "Wednesday": {
    "06:00 AM": "wake up & walk",
    "07:00 AM": "study gk",
    "08:00 AM": "",
    "09:00 AM": "english",
    "10:00 AM": "",
    "11:00 AM": "",
    "12:00 PM": "",
    "01:00 PM": "",
    "02:00 PM": "break",
    "03:00 PM": "maths",
    "04:00 PM": "",
    "05:00 PM": "All daily quizz",
    "06:00 PM": "",
    "07:00 PM": "",
    "08:00 PM": "",
    "09:00 PM": "Mock tests"
  },
  "Thursday": {
    "06:00 AM": "wake up & walk",
    "07:00 AM": "study gk",
    "08:00 AM": "",
    "09:00 AM": "",
    "10:00 AM": "break",
    "11:00 AM": "",
    "12:00 PM": "",
    "01:00 PM": "",
    "02:00 PM": "break",
    "03:00 PM": "",
    "04:00 PM": "",
    "05:00 PM": "All daily quizz",
    "06:00 PM": "",
    "07:00 PM": "",
    "08:00 PM": "",
    "09:00 PM": ""
  },
  "Friday": {
    "06:00 AM": "wake up & walk",
    "07:00 AM": "study gk",
    "08:00 AM": "breakfast",
    "09:00 AM": "maths",
    "10:00 AM": "english",
    "11:00 AM": "",
    "12:00 PM": "",
    "01:00 PM": "namaz",
    "02:00 PM": "break",
    "03:00 PM": "",
    "04:00 PM": "",
    "05:00 PM": "All daily quizz",
    "06:00 PM": "",
    "07:00 PM": "",
    "08:00 PM": "",
    "09:00 PM": "Mock tests"
  },
  "Saturday": {
    "06:00 AM": "wake up & walk",
    "07:00 AM": "study gk",
    "08:00 AM": "",
    "09:00 AM": "maths",
    "10:00 AM": "break",
    "11:00 AM": "",
    "12:00 PM": "",
    "01:00 PM": "",
    "02:00 PM": "break",
    "03:00 PM": "",
    "04:00 PM": "",
    "05:00 PM": "All daily quizz",
    "06:00 PM": "G.k",
    "07:00 PM": "Maths",
    "08:00 PM": "",
    "09:00 PM": ""
  },
  "Sunday": {
    "06:00 AM": "wake up & walk",
    "07:00 AM": "study gk",
    "08:00 AM": "",
    "09:00 AM": "",
    "10:00 AM": "",
    "11:00 AM": "",
    "12:00 PM": "",
    "01:00 PM": "",
    "02:00 PM": "break",
    "03:00 PM": "",
    "04:00 PM": "",
    "05:00 PM": "All daily quizz",
    "06:00 PM": "",
    "07:00 PM": "",
    "08:00 PM": "",
    "09:00 PM": ""
  }
}